{
  "taxYear": 2026,
  "eitc": [
    {
      "qualifyingChildren": 0,
      "phaseInRate": 0.0765,
      "maxCredit": 664,
      "phaseOutRate": 0.0765,
      "phaseOutThresholdSingle": 10860,
      "phaseOutThresholdMarried": 18140
    },
    {
      "qualifyingChildren": 1,
      "phaseInRate": 0.34,
      "maxCredit": 4427,
      "phaseOutRate": 0.1598,
      "phaseOutThresholdSingle": 23890,
      "phaseOutThresholdMarried": 31160
    },
    {
      "qualifyingChildren": 2,
      "phaseInRate": 0.4,
      "maxCredit": 7316,
      "phaseOutRate": 0.2106,
      "phaseOutThresholdSingle": 23890,
      "phaseOutThresholdMarried": 31160
    },
    {
      "qualifyingChildren": 3,
      "phaseInRate": 0.45,
      "maxCredit": 8231,
      "phaseOutRate": 0.2106,
      "phaseOutThresholdSingle": 23890,
      "phaseOutThresholdMarried": 31160
    }
  ],
  "childTaxCredit": {
    "perChild": 2200,
    "refundableCap": 1700,
    "phaseOutThresholdSingle": 200000,
    "phaseOutThresholdMarried": 400000,
    "phaseOutPerThousand": 50
  },
  "citation": {
    "sourceUrl": "https://www.irs.gov/pub/irs-drop/rp-25-32.pdf",
    "sourceDocument": "IRS Revenue Procedure 2025-32 (2026 EITC) and IRC §24 (Child Tax Credit, $2,200 per child under the One Big Beautiful Bill Act)",
    "effectiveYear": 2026,
    "dateRetrieved": "2026-06-02"
  }
}
